topsis/__init__.py
Topsis_Aashish_101917110-1.0.0.dist-info/LICENSE
Topsis_Aashish_101917110-1.0.0.dist-info/METADATA
Topsis_Aashish_101917110-1.0.0.dist-info/WHEEL
Topsis_Aashish_101917110-1.0.0.dist-info/top_level.txt
Topsis_Aashish_101917110-1.0.0.dist-info/RECORD
